pr_reviewer/__init__.py
pr_reviewer/pr_reviewer.py
pr_reviewer/utils/__init__.py
pr_reviewer/utils/config.py
afila_pr_reviewer-0.1.0.dist-info/LICENSE
afila_pr_reviewer-0.1.0.dist-info/METADATA
afila_pr_reviewer-0.1.0.dist-info/WHEEL
afila_pr_reviewer-0.1.0.dist-info/entry_points.txt
afila_pr_reviewer-0.1.0.dist-info/top_level.txt
afila_pr_reviewer-0.1.0.dist-info/RECORD
