Metadata-Version: 2.2
Name: afila-pr-reviewer
Version: 0.1.0
Summary: A tool for reviewing GitHub PRs using OpenAI, developed by AFILALABS
Author-email: AFILALABS <team@afilalabs.com>
License: MIT
Project-URL: Homepage, https://github.com/AFILALABS/pr-reviewer
Project-URL: Bug Tracker, https://github.com/AFILALABS/pr-reviewer/issues
Keywords: github,pull request,code review,openai,ai
Classifier: Programming Language :: Python :: 3
Classifier: Programming Language :: Python :: 3.7
Classifier: Programming Language :: Python :: 3.8
Classifier: Programming Language :: Python :: 3.9
Classifier: License :: OSI Approved :: MIT License
Classifier: Operating System :: OS Independent
Classifier: Development Status :: 4 - Beta
Classifier: Intended Audience :: Developers
Classifier: Topic :: Software Development :: Quality Assurance
Requires-Python: >=3.7
License-File: LICENSE
Requires-Dist: requests>=2.25.0
Requires-Dist: urllib3>=1.26.0
Requires-Dist: keyring>=23.0.0
